mquad/__init__.py
mquad/mquad.py
mquad/mquad_CLI.py
mquad/mquad_batch_mixbin.py
mquad/mquad_utils.py
mquad/version.py
mquad-0.1.8.dist-info/LICENSE
mquad-0.1.8.dist-info/METADATA
mquad-0.1.8.dist-info/WHEEL
mquad-0.1.8.dist-info/entry_points.txt
mquad-0.1.8.dist-info/top_level.txt
mquad-0.1.8.dist-info/RECORD
