Metadata-Version: 2.1
Name: mquad
Version: 0.1.8
Summary: MQuad - Mixture Modelling for Mitochondrial Mutation detection
Home-page: https://github.com/aaronkwc/MQuad
Author: Aaron Kwok
Author-email: aaronkwc@connect.hku.hk
License: Apache-2.0
Keywords: mitochondrial mutation,single-cell omics data,binomial mixture model,model selection
License-File: LICENSE
Requires-Dist: numpy >=1.9.0
Requires-Dist: scipy >=1.4.0
Requires-Dist: matplotlib
Requires-Dist: BBMix >=0.2.1
Requires-Dist: vireoSNP
Requires-Dist: kneed
Requires-Dist: pandas
Requires-Dist: seaborn
Requires-Dist: scikit-learn
Provides-Extra: docs
Requires-Dist: sphinx-bootstrap-theme ; extra == 'docs'
